Metadata-Version: 2.1
Name: control-toolbox
Version: 0.1.0
Summary: Python Control System Toolbox
Home-page: https://control-toolbox.readthedocs.io/
Author: Rushad Mehta
Author-email: rushadmehta16@gmail.com
License: MIT
Download-URL: https://github.com/rushad7/control-toolbox/archive/v0.1.0.tar.gz
Keywords: Control Systems,Python Control Toolbox,System Simulation
Platform: UNKNOWN
Classifier: Development Status :: 3 - Alpha
Classifier: Intended Audience :: Science/Research
Classifier: Topic :: Scientific/Engineering
Classifier: License :: OSI Approved :: MIT License
Classifier: Programming Language :: Python :: 3.6
Classifier: Programming Language :: Python :: 3.7
